Goodjob-0.1.0.dist-info/WHEEL
Goodjob-0.1.0.dist-info/RECORD
Goodjob-0.1.0.dist-info/METADATA
Goodjob-0.1.0.dist-info/metadata.json
Goodjob-0.1.0.dist-info/top_level.txt
Goodjob-0.1.0.dist-info/DESCRIPTION.rst
Goodjob-0.1.0.dist-info/entry_points.txt
goodjob/cors.py
goodjob/constants.py
goodjob/utils.py
goodjob/__init__.py
goodjob/api.py
goodjob/db.py
goodjob/xx_python_command.py
goodjob/wsgi.py
goodjob/operators/__init__.py
goodjob/operators/python.py
goodjob/operators/base.py
goodjob/operators/shell.py
goodjob/operators/manager.py
goodjob/config/__init__.py
goodjob/config/default.py
goodjob/cli/executor.py
goodjob/cli/__init__.py
goodjob/celery/app.py
goodjob/celery/__init__.py
goodjob/celery/schedulers.py
goodjob/celery/config.py
goodjob/resources/__init__.py
goodjob/jobs/resource.py
goodjob/jobs/executor.py
goodjob/jobs/__init__.py
goodjob/jobs/notifier.py
goodjob/jobs/models.py
goodjob/logs/resource.py
goodjob/logs/__init__.py
