Metadata-Version: 2.0
Name: Goodjob
Version: 0.1.0
Summary: A service for executing asynchronous jobs.
Home-page: https://github.com/RussellLuo/goodjob
Author: RussellLuo
Author-email: luopeng.he@gmail.com
License: MIT
Keywords: Asynchronous Job,Redis Queue,Python
Platform: UNKNOWN
Requires-Dist: celery (==3.1.17)
Requires-Dist: redis (==2.10.3)
Requires-Dist: restart-mongo
Requires-Dist: restart-crossdomain
Requires-Dist: mongoengine
Requires-Dist: click (==4.0)
